{
  "id": "marco-26-s-1",
  "title": "26-S-1 · Señal próxima sección «01 · El principio» (mitad izq · flecha →) — Bici / combustión (4.50×2.50 m)",
  "createdAt": "2026-06-04T00:00:00.000Z",
  "pageComponentId": "proxima-sala",
  "theme": "light",
  "dimensions": {
    "trimWidthMm": 4500,
    "trimHeightMm": 3000,
    "bleedMm": 10,
    "safeMarginMm": 0,
    "cropMarks": false
  },
  "dpi": 24,
  "color": {
    "mode": "cmyk",
    "iccProfile": "icc/PSOuncoated_v3_FOGRA52.icc",
    "renderIntent": "perceptual",
    "pdfxVariant": "x1a"
  },
  "props": {
    "frameWallInvId": 26,
    "wallId": "wall-25",
    "frameId": "26-S-1",
    "side": 1,
    "invId": 26,
    "readingDistanceM": 4,
    "eyebrow": "Próxima sección",
    "num": "01",
    "sala": "El principio",
    "salaLines": ["El principio"],
    "arrow": "right",
    "showFilete": false,
    "showTick": false,
    "blockCenterXFraction": 0.25,
    "eyeBandFraction": 0.5
  }
}
